CHANGES.txt
MANIFEST.in
requirements.txt
setup.py
tsquare/__init__.py
tsquare/core.py
tsquare/parsers.py
tsquare.egg-info/PKG-INFO
tsquare.egg-info/SOURCES.txt
tsquare.egg-info/dependency_links.txt
tsquare.egg-info/requires.txt
tsquare.egg-info/top_level.txt