Metadata-Version: 1.0
Name: tsquare
Version: 0.2.2
Summary: Python TSquare API bindings
Home-page: https://github.com/swgillespie/tsquare
Author: Sean Gillespie
Author-email: sean.william.g@gmail.com
License: MIT
Platform: UNKNOWN
